{
    "name": "Base string",
    "osc": [
        {
            "oct": 7,
            "vol": 255,
            "waveform": 2
        },
        {
            "oct": 8,
            "detune": 18,
            "vol": 255,
            "waveform": 2
        }
    ],
    "env": {
        "attack": 100000,
        "sustain": 56363,
        "release": 100000,
        "master": 199
    },
    "fx": {
        "filter": 2,
        "freq": 200,
        "resonance": 254,
        "delay_time": 8,
        "delay_amt": 24
    },
    "lfo": {}
}